{"guild":{"member":[{"memberContribution":[{"type":2,"currentValue":"456","lifetimeValue":"1114606"},{"type":3,"currentValue":"0","lifetimeValue":"5865"},{"type":1,"currentValue":"2014","lifetimeValue":"1933072"}],"seasonStatus":[{"seasonId":"4zone_5v5_ga2_c3s1_44a","eventInstanceId":"GA2_SEASON_44A:O1694466000000","league":"CARBONITE","wins":0,"losses":0,"seasonPoints":1718,"division":15,"joinTime":"1694539172000","endTime":"1696798800000","remove":false,"rank":17438},{"seasonId":"4zone_3v3_ga2_c3s1_45a","eventInstanceId":"GA2_SEASON_45A:O1696885200000","league":"CARBONITE","wins":0,"losses":0,"seasonPoints":2493,"division":20,"joinTime":"1696894241000","endTime":"1699218000000","remove":false,"rank":8217},{"seasonId":"4zone_5v5_ga2_c3s1_46a","eventInstanceId":"GA2_SEASON_46A:O1699308000000","league":"CARBONITE","wins":0,"losses":0,"seasonPoints":1727,"division":20,"joinTime":"1699310850000","endTime":"1701640800000","remove":false,"rank":0}],"playerId":"1XWZqKsnT-C8qNWSk7mhqA","playerName":"FR3ED0M","playerLevel":85,"memberLevel":2,"guildXp":0,"lastActivityTime":"1699839519000","squadPower":163579,"guildJoinTime":"1508543364","galacticPower":"7675152","playerTitle":"PLAYERTITLE_LOYAL_FRIEND","playerPortrait":"PLAYERPORTRAIT_ZAALBAR","lifetimeSeasonScore":"669328","leagueId":"CARBONITE","shipGalacticPower":"3195353","characterGalacticPower":"4479799"},{"memberContribution":[{"type":2,"currentValue":"208","lifetimeValue":"977816"},{"type":3,"currentValue":"0","lifetimeValue":"3488"},{"type":1,"currentValue":"86","lifetimeValue":"2240265"}],"seasonStatus":[{"seasonId":"4zone_5v5_ga2_c3s1_44a","eventInstanceId":"GA2_SEASON_44A:O1694466000000","league":"CHROMIUM","wins":0,"losses":0,"seasonPoints":3768,"division":10,"joinTime":"1694466820000","endTime":"1696798800000","remove":false,"rank":11011},{"seasonId":"4zone_3v3_ga2_c3s1_45a","eventInstanceId":"GA2_SEASON_45A:O1696885200000","league":"CHROMIUM","wins":0,"losses":0,"seasonPoints":6146,"division":15,"joinTime":"1696885340000","endTime":"1699218000000","remove":false,"rank":6047},{"seasonId":"4zone_5v5_ga2_c3s1_46a","eventInstanceId":"GA2_SEASON_46A:O1699308000000","league":"CHROMIUM","wins":0,"losses":0,"seasonPoints":1357,"division":15,"joinTime":"1699308011000","endTime":"1701640800000","remove":false,"rank":0}],"playerId":"C-XlXEPHQcO6ugoZGaNvyQ","playerName":"wutchuneed","playerLevel":85,"memberLevel":2,"guildXp":0,"lastActivityTime":"1699842180000","squadPower":162035,"guildJoinTime":"1513203762","galacticPower":"8079956","playerTitle":"PLAYERTITLE_BAD_BATCH","playerPortrait":"PLAYERPORTRAIT_MANDO","lifetimeSeasonScore":"511367","leagueId":"CHROMIUM","shipGalacticPower":"3383998","characterGalacticPower":"4695958"},{"memberContribution":[{"type":2,"currentValue":"0","lifetimeValue":"1126714"},{"type":3,"currentValue":"0","lifetimeValue":"3235"},{"type":1,"currentValue":"0","lifetimeValue":"2291956"}],"seasonStatus":[{"seasonId":"4zone_5v5_ga2_c3s1_44a","eventInstanceId":"GA2_SEASON_44A:O1694466000000","league":"AURODIUM","wins":0,"losses":0,"seasonPoints":6678,"division":15,"joinTime":"1694491395000","endTime":"1696798800000","remove":false,"rank":3286},{"seasonId":"4zone_3v3_ga2_c3s1_45a","eventInstanceId":"GA2_SEASON_45A:O1696885200000","league":"AURODIUM","wins":0,"losses":0,"seasonPoints":5650,"division":15,"joinTime":"1696910508000","endTime":"1699218000000","remove":false,"rank":5642},{"seasonId":"4zone_5v5_ga2_c3s1_46a","eventInstanceId":"GA2_SEASON_46A:O1699308000000","league":"AURODIUM","wins":0,"losses":0,"seasonPoints":644,"division":20,"joinTime":"1699333339000","endTime":"1701640800000","remove":false,"rank":0}],"playerId":"89WBsfisSRWMfs1v-hQ2gg","playerName":"Delmon Enz","playerLevel":85,"memberLevel":2,"guildXp":0,"lastActivityTime":"1699823403000","squadPower":178482,"guildJoinTime":"1520623848","galacticPower":"8806885","playerTitle":"PLAYERTITLE_PITFIGHTER","playerPortrait":"PLAYERPORTRAIT_NIGHTSISTERS_VENTRESS","lifetimeSeasonScore":"543187","leagueId":"AURODIUM","shipGalacticPower":"3652925","characterGalacticPower":"5153960"},{"memberContribution":[{"type":2,"currentValue":"32","lifetimeValue":"627280"},{"type":3,"currentValue":"0","lifetimeValue":"2945"},{"type":1,"currentValue":"86","lifetimeValue":"1798844"}],"seasonStatus":[{"seasonId":"4zone_5v5_ga2_c3s1_44a","eventInstanceId":"GA2_SEASON_44A:O1694466000000","league":"CARBONITE","wins":0,"losses":0,"seasonPoints":5388,"division":25,"joinTime":"1694491742000","endTime":"1696798800000","remove":false,"rank":3782},{"seasonId":"4zone_3v3_ga2_c3s1_45a","eventInstanceId":"GA2_SEASON_45A:O1696885200000","league":"BRONZIUM","wins":0,"losses":0,"seasonPoints":8001,"division":15,"joinTime":"1696888861000","endTime":"1699218000000","remove":false,"rank":9621},{"seasonId":"4zone_5v5_ga2_c3s1_46a","eventInstanceId":"GA2_SEASON_46A:O1699308000000","league":"BRONZIUM","wins":0,"losses":0,"seasonPoints":2679,"division":20,"joinTime":"1699335160000","endTime":"1701640800000","remove":false,"rank":0}],"playerId":"ozpL5CKcRe-9HcECTxP3DQ","playerName":"Bombastic Brandon","playerLevel":85,"memberLevel":2,"guildXp":0,"lastActivityTime":"1699836358000","squadPower":142204,"guildJoinTime":"1539569412","galacticPower":"6740965","playerTitle":"PLAYERTITLE_DARKLORD","playerPortrait":"PLAYERPORTRAIT_DARTHREVAN","lifetimeSeasonScore":"468086","leagueId":"BRONZIUM","shipGalacticPower":"2693255","characterGalacticPower":"4047710"},{"memberContribution":[{"type":2,"currentValue":"0","lifetimeValue":"675202"},{"type":3,"currentValue":"0","lifetimeValue":"648"},{"type":1,"currentValue":"86","lifetimeValue":"1499244"}],"seasonStatus":[{"seasonId":"4zone_5v5_ga2_c3s1_44a","eventInstanceId":"GA2_SEASON_44A:O1694466000000","league":"CHROMIUM","wins":0,"losses":0,"seasonPoints":3522,"division":25,"joinTime":"1694477038000","endTime":"1696798800000","remove":false,"rank":1332},{"seasonId":"4zone_3v3_ga2_c3s1_45a","eventInstanceId":"GA2_SEASON_45A:O1696885200000","league":"AURODIUM","wins":0,"losses":0,"seasonPoints":4206,"division":10,"joinTime":"1696886953000","endTime":"1699218000000","remove":false,"rank":5837},{"seasonId":"4zone_5v5_ga2_c3s1_46a","eventInstanceId":"GA2_SEASON_46A:O1699308000000","league":"AURODIUM","wins":0,"losses":0,"seasonPoints":476,"division":10,"joinTime":"1699319683000","endTime":"1701640800000","remove":false,"rank":0}],"playerId":"R6ldSBtLR2aVqWtSPbFfpg","playerName":"Sraspencer","playerLevel":85,"memberLevel":2,"guildXp":0,"lastActivityTime":"1699840414000","squadPower":187079,"guildJoinTime":"1554589890","galacticPower":"6964672","playerTitle":"PLAYERTITLE_GLLUKE_EVENT","playerPortrait":"PLAYERPORTRAIT_JEDIKNIGHTLUKE","lifetimeSeasonScore":"594286","leagueId":"AURODIUM","shipGalacticPower":"2940610","characterGalacticPower":"4024062"},{"memberContribution":[{"type":2,"currentValue":"0","lifetimeValue":"656886"},{"type":3,"currentValue":"0","lifetimeValue":"1521"},{"type":1,"currentValue":"0","lifetimeValue":"1504305"}],"seasonStatus":[{"seasonId":"4zone_5v5_ga2_c3s1_44a","eventInstanceId":"GA2_SEASON_44A:O1694466000000","league":"CHROMIUM","wins":0,"losses":0,"seasonPoints":1440,"division":10,"joinTime":"1694473965000","endTime":"1696798800000","remove":false,"rank":2677},{"seasonId":"4zone_3v3_ga2_c3s1_45a","eventInstanceId":"GA2_SEASON_45A:O1696885200000","league":"CHROMIUM","wins":0,"losses":0,"seasonPoints":709,"division":5,"joinTime":"1696904359000","endTime":"1699218000000","remove":false,"rank":8249},{"seasonId":"4zone_5v5_ga2_c3s1_46a","eventInstanceId":"GA2_SEASON_46A:O1699308000000","league":"BRONZIUM","wins":0,"losses":0,"seasonPoints":0,"division":15,"joinTime":"1699308341000","endTime":"1701640800000","remove":false,"rank":0}],"playerId":"hakEMBtaTqqFoXPldV3UIg","playerName":"seanmitch","playerLevel":85,"memberLevel":2,"guildXp":0,"lastActivityTime":"1699829963000","squadPower":174497,"guildJoinTime":"1585787442","galacticPower":"8529794","playerTitle":"PLAYERTITLE_GLSLKR_QUEST_002","playerPortrait":"PLAYERPORTRAIT_GLKYLOREN","lifetimeSeasonScore":"480457","leagueId":"BRONZIUM","shipGalacticPower":"3643479","characterGalacticPower":"4886315"},{"memberContribution":[{"type":2,"currentValue":"0","lifetimeValue":"501372"},{"type":3,"currentValue":"0","lifetimeValue":"1075"},{"type":1,"currentValue":"96","lifetimeValue":"1256857"}],"seasonStatus":[{"seasonId":"4zone_5v5_ga2_c3s1_44a","eventInstanceId":"GA2_SEASON_44A:O1694466000000","league":"BRONZIUM","wins":0,"losses":0,"seasonPoints":2880,"division":10,"joinTime":"1694466025000","endTime":"1696798800000","remove":false,"rank":1099},{"seasonId":"4zone_3v3_ga2_c3s1_45a","eventInstanceId":"GA2_SEASON_45A:O1696885200000","league":"BRONZIUM","wins":0,"losses":0,"seasonPoints":2969,"division":10,"joinTime":"1696887892000","endTime":"1699218000000","remove":false,"rank":14851},{"seasonId":"4zone_5v5_ga2_c3s1_46a","eventInstanceId":"GA2_SEASON_46A:O1699308000000","league":"BRONZIUM","wins":0,"losses":0,"seasonPoints":2415,"division":15,"joinTime":"1699309190000","endTime":"1701640800000","remove":false,"rank":0}],"playerId":"vOlHHoAKQLOluUUMh_GsCw","playerName":"Guark Qarnazt","playerLevel":85,"memberLevel":2,"guildXp":0,"lastActivityTime":"1699840896000","squadPower":121375,"guildJoinTime":"1602459443","galacticPower":"7296456","playerTitle":"PLAYERTITLE_GLSLKR_QUEST_003","playerPortrait":"PLAYERPORTRAIT_WICKET","lifetimeSeasonScore":"156529","leagueId":"BRONZIUM","shipGalacticPower":"3057749","characterGalacticPower":"4238707"},{"memberContribution":[{"type":2,"currentValue":"0","lifetimeValue":"539868"},{"type":3,"currentValue":"0","lifetimeValue":"285"},{"type":1,"currentValue":"0","lifetimeValue":"1033878"}],"seasonStatus":[{"seasonId":"4zone_5v5_ga2_c3s1_44a","eventInstanceId":"GA2_SEASON_44A:O1694466000000","league":"BRONZIUM","wins":0,"losses":0,"seasonPoints":1199,"division":10,"joinTime":"1694498494000","endTime":"1696798800000","remove":false,"rank":13258},{"seasonId":"4zone_3v3_ga2_c3s1_45a","eventInstanceId":"GA2_SEASON_45A:O1696885200000","league":"BRONZIUM","wins":0,"losses":0,"seasonPoints":921,"division":5,"joinTime":"1696927242000","endTime":"1699218000000","remove":false,"rank":2679},{"seasonId":"4zone_5v5_ga2_c3s1_46a","eventInstanceId":"GA2_SEASON_46A:O1699308000000","league":"CARBONITE","wins":0,"losses":0,"seasonPoints":1097,"division":25,"joinTime":"1699383586000","endTime":"1701640800000","remove":false,"rank":0}],"playerId":"_7jEuSqeRpy4kADdLvAS4w","playerName":"szerted","playerLevel":85,"memberLevel":2,"guildXp":0,"lastActivityTime":"1699812951000","squadPower":169411,"guildJoinTime":"1620498100","galacticPower":"4659000","playerTitle":"PLAYERTITLE_GRANDARENA_INTRO","playerPortrait":"PLAYERPORTRAIT_C3POLEGENDARY","lifetimeSeasonScore":"108482","leagueId":"CARBONITE","shipGalacticPower":"1746815","characterGalacticPower":"2912185"},{"memberContribution":[{"type":2,"currentValue":"0","lifetimeValue":"503800"},{"type":3,"currentValue":"0","lifetimeValue":"304"},{"type":1,"currentValue":"0","lifetimeValue":"857358"}],"seasonStatus":[{"seasonId":"4zone_5v5_ga2_c3s1_44a","eventInstanceId":"GA2_SEASON_44A:O1694466000000","league":"CHROMIUM","wins":0,"losses":0,"seasonPoints":8644,"division":15,"joinTime":"1694538440000","endTime":"1696798800000","remove":false,"rank":6565},{"seasonId":"4zone_3v3_ga2_c3s1_45a","eventInstanceId":"GA2_SEASON_45A:O1696885200000","league":"CHROMIUM","wins":0,"losses":0,"seasonPoints":5602,"division":20,"joinTime":"1696885584000","endTime":"1699218000000","remove":false,"rank":1797},{"seasonId":"4zone_5v5_ga2_c3s1_46a","eventInstanceId":"GA2_SEASON_46A:O1699308000000","league":"CHROMIUM","wins":0,"losses":0,"seasonPoints":692,"division":25,"joinTime":"1699308004000","endTime":"1701640800000","remove":false,"rank":0}],"playerId":"Dvt29c9pRt2i9hzt8hw2Ew","playerName":"Matt","playerLevel":85,"memberLevel":2,"guildXp":0,"lastActivityTime":"1699819124000","squadPower":172146,"guildJoinTime":"1622399166","galacticPower":"5460809","playerTitle":"PLAYERTITLE_GLJMK_QUEST_002","playerPortrait":"PLAYERPORTRAIT_BD1","lifetimeSeasonScore":"94677","leagueId":"CHROMIUM","shipGalacticPower":"2228331","characterGalacticPower":"3232478"},{"memberContribution":[{"type":2,"currentValue":"0","lifetimeValue":"406126"},{"type":3,"currentValue":"0","lifetimeValue":"28"},{"type":1,"currentValue":"96","lifetimeValue":"895877"}],"seasonStatus":[{"seasonId":"4zone_5v5_ga2_c3s1_44a","eventInstanceId":"GA2_SEASON_44A:O1694466000000","league":"CHROMIUM","wins":0,"losses":0,"seasonPoints":4855,"division":10,"joinTime":"1694469093000","endTime":"1696798800000","remove":false,"rank":11767},{"seasonId":"4zone_3v3_ga2_c3s1_45a","eventInstanceId":"GA2_SEASON_45A:O1696885200000","league":"CHROMIUM","wins":0,"losses":0,"seasonPoints":8321,"division":10,"joinTime":"1696898642000","endTime":"1699218000000","remove":false,"rank":9122},{"seasonId":"4zone_5v5_ga2_c3s1_46a","eventInstanceId":"GA2_SEASON_46A:O1699308000000","league":"CHROMIUM","wins":0,"losses":0,"seasonPoints":952,"division":15,"joinTime":"1699311186000","endTime":"1701640800000","remove":false,"rank":0}],"playerId":"6cFRV0H5Ro2ME9vLZg3Lug","playerName":"MonkeyPants57","playerLevel":85,"memberLevel":2,"guildXp":0,"lastActivityTime":"1699840795000","squadPower":182791,"guildJoinTime":"1623699219","galacticPower":"5456579","playerTitle":"PLAYERTITLE_GRANDARENA_ADVANCED","playerPortrait":"PLAYERPORTRAIT_GRANDARENA_ADVANCED","lifetimeSeasonScore":"129043","leagueId":"CHROMIUM","shipGalacticPower":"2196262","characterGalacticPower":"3260317"},{"memberContribution":[{"type":2,"currentValue":"0","lifetimeValue":"475946"},{"type":3,"currentValue":"0","lifetimeValue":"171"},{"type":1,"currentValue":"0","lifetimeValue":"915319"}],"seasonStatus":[{"seasonId":"4zone_5v5_ga2_c3s1_44a","eventInstanceId":"GA2_SEASON_44A:O1694466000000","league":"CHROMIUM","wins":0,"losses":0,"seasonPoints":7787,"division":15,"joinTime":"1694466111000","endTime":"1696798800000","remove":false,"rank":1209},{"seasonId":"4zone_3v3_ga2_c3s1_45a","eventInstanceId":"GA2_SEASON_45A:O1696885200000","league":"CHROMIUM","wins":0,"losses":0,"seasonPoints":6523,"division":20,"joinTime":"1696891742000","endTime":"1699218000000","remove":false,"rank":3161},{"seasonId":"4zone_5v5_ga2_c3s1_46a","eventInstanceId":"GA2_SEASON_46A:O1699308000000","league":"CHROMIUM","wins":0,"losses":0,"seasonPoints":384,"division":20,"joinTime":"1699308692000","endTime":"1701640800000","remove":false,"rank":0}],"playerId":"-RJCmgceSQCOZECssc_Tzg","playerName":"Eldrin Wolfe","playerLevel":85,"memberLevel":2,"guildXp":0,"lastActivityTime":"1699835219000","squadPower":159682,"guildJoinTime":"1625025620","galacticPower":"7861885","playerTitle":"PLAYERTITLE_JEDI_GENERAL","playerPortrait":"PLAYERPORTRAIT_GLKENOBI","lifetimeSeasonScore":"217595","leagueId":"CHROMIUM","shipGalacticPower":"3468489","characterGalacticPower":"4393396"},{"memberContribution":[{"type":2,"currentValue":"0","lifetimeValue":"474858"},{"type":3,"currentValue":"0","lifetimeValue":"487"},{"type":1,"currentValue":"99","lifetimeValue":"995019"}],"seasonStatus":[{"seasonId":"4zone_5v5_ga2_c3s1_44a","eventInstanceId":"GA2_SEASON_44A:O1694466000000","league":"AURODIUM","wins":0,"losses":0,"seasonPoints":8697,"division":10,"joinTime":"1694470229000","endTime":"1696798800000","remove":false,"rank":4940},{"seasonId":"4zone_3v3_ga2_c3s1_45a","eventInstanceId":"GA2_SEASON_45A:O1696885200000","league":"AURODIUM","wins":0,"losses":0,"seasonPoints":10735,"division":15,"joinTime":"1696887385000","endTime":"1699218000000","remove":false,"rank":6261},{"seasonId":"4zone_5v5_ga2_c3s1_46a","eventInstanceId":"GA2_SEASON_46A:O1699308000000","league":"AURODIUM","wins":0,"losses":0,"seasonPoints":3885,"division":15,"joinTime":"1699308158000","endTime":"1701640800000","remove":false,"rank":0}],"playerId":"YAhQkWmDTU2wKDAW42WYLQ","playerName":"hugepog","playerLevel":85,"memberLevel":2,"guildXp":0,"lastActivityTime":"1699842300000","squadPower":161239,"guildJoinTime":"1625347003","galacticPower":"6858312","playerTitle":"PLAYERTITLE_GLJABBA_EVENT","playerPortrait":"PLAYERPORTRAIT_SITHTROOPER","lifetimeSeasonScore":"175912","leagueId":"AURODIUM","shipGalacticPower":"2933086","characterGalacticPower":"3925226"},{"memberContribution":[{"type":2,"currentValue":"96","lifetimeValue":"365872"},{"type":3,"currentValue":"0","lifetimeValue":"45"},{"type":1,"currentValue":"86","lifetimeValue":"948245"}],"seasonStatus":[{"seasonId":"4zone_5v5_ga2_c3s1_44a","eventInstanceId":"GA2_SEASON_44A:O1694466000000","league":"BRONZIUM","wins":0,"losses":0,"seasonPoints":4028,"division":5,"joinTime":"1694486707000","endTime":"1696798800000","remove":false,"rank":13657},{"seasonId":"4zone_3v3_ga2_c3s1_45a","eventInstanceId":"GA2_SEASON_45A:O1696885200000","league":"CARBONITE","wins":0,"losses":0,"seasonPoints":7249,"division":25,"joinTime":"1696900577000","endTime":"1699218000000","remove":false,"rank":160},{"seasonId":"4zone_5v5_ga2_c3s1_46a","eventInstanceId":"GA2_SEASON_46A:O1699308000000","league":"BRONZIUM","wins":0,"losses":0,"seasonPoints":2098,"division":25,"joinTime":"1699310960000","endTime":"1701640800000","remove":false,"rank":0}],"playerId":"YkPMDjVVRW6bahLoyWAoLg","playerName":"Kned","playerLevel":85,"memberLevel":2,"guildXp":0,"lastActivityTime":"1699841660000","squadPower":166689,"guildJoinTime":"1626119671","galacticPower":"5750380","playerTitle":"PLAYERTITLE_DARKLORD","playerPortrait":"PLAYERPORTRAIT_KYLOMASKED","lifetimeSeasonScore":"61744","leagueId":"BRONZIUM","shipGalacticPower":"2562811","characterGalacticPower":"3187569"},{"memberContribution":[{"type":2,"currentValue":"204","lifetimeValue":"485672"},{"type":3,"currentValue":"0","lifetimeValue":"826"},{"type":1,"currentValue":"111","lifetimeValue":"1001234"}],"seasonStatus":[{"seasonId":"4zone_5v5_ga2_c3s1_44a","eventInstanceId":"GA2_SEASON_44A:O1694466000000","league":"CHROMIUM","wins":0,"losses":0,"seasonPoints":6866,"division":25,"joinTime":"1694466151000","endTime":"1696798800000","remove":false,"rank":2039},{"seasonId":"4zone_3v3_ga2_c3s1_45a","eventInstanceId":"GA2_SEASON_45A:O1696885200000","league":"AURODIUM","wins":0,"losses":0,"seasonPoints":8686,"division":10,"joinTime":"1696894120000","endTime":"1699218000000","remove":false,"rank":6451},{"seasonId":"4zone_5v5_ga2_c3s1_46a","eventInstanceId":"GA2_SEASON_46A:O1699308000000","league":"AURODIUM","wins":0,"losses":0,"seasonPoints":3317,"division":10,"joinTime":"1699315188000","endTime":"1701640800000","remove":false,"rank":0}],"playerId":"n8Px3_P4RnG6Z9RNpoKSVw","playerName":"Dace Joy","playerLevel":85,"memberLevel":2,"guildXp":0,"lastActivityTime":"1699842344000","squadPower":172510,"guildJoinTime":"1626744924","galacticPower":"6919324","playerTitle":"PLAYERTITLE_SITHSMITER","playerPortrait":"PLAYERPORTRAIT_GLLUKE","lifetimeSeasonScore":"74702","leagueId":"AURODIUM","shipGalacticPower":"2970066","characterGalacticPower":"3949258"},{"memberContribution":[{"type":2,"currentValue":"0","lifetimeValue":"364334"},{"type":3,"currentValue":"0","lifetimeValue":"77"},{"type":1,"currentValue":"0","lifetimeValue":"839688"}],"seasonStatus":[{"seasonId":"4zone_5v5_ga2_c3s1_44a","eventInstanceId":"GA2_SEASON_44A:O1694466000000","league":"CARBONITE","wins":0,"losses":0,"seasonPoints":1308,"division":20,"joinTime":"1694556490000","endTime":"1696798800000","remove":false,"rank":8177},{"seasonId":"4zone_3v3_ga2_c3s1_45a","eventInstanceId":"GA2_SEASON_45A:O1696885200000","league":"CARBONITE","wins":0,"losses":0,"seasonPoints":3139,"division":20,"joinTime":"1696901472000","endTime":"1699218000000","remove":false,"rank":8110},{"seasonId":"4zone_5v5_ga2_c3s1_46a","eventInstanceId":"GA2_SEASON_46A:O1699308000000","league":"CARBONITE","wins":0,"losses":0,"seasonPoints":450,"division":25,"joinTime":"1699363940000","endTime":"1701640800000","remove":false,"rank":0}],"playerId":"FOo6YGN8QjC2fjgKQC4lFQ","playerName":"Revan111","playerLevel":85,"memberLevel":2,"guildXp":0,"lastActivityTime":"1699819607000","squadPower":156406,"guildJoinTime":"1629379782","galacticPower":"4818671","playerTitle":"PLAYERTITLE_DARKLORD","playerPortrait":"PLAYERPORTRAIT_DARTHREVAN","lifetimeSeasonScore":"32101","leagueId":"CARBONITE","shipGalacticPower":"1906386","characterGalacticPower":"2912285"},{"memberContribution":[{"type":2,"currentValue":"600","lifetimeValue":"422044"},{"type":3,"currentValue":"0","lifetimeValue":"1214"},{"type":1,"currentValue":"86","lifetimeValue":"881846"}],"seasonStatus":[{"seasonId":"4zone_5v5_ga2_c3s1_44a","eventInstanceId":"GA2_SEASON_44A:O1694466000000","league":"KYBER","wins":0,"losses":0,"seasonPoints":9302,"division":15,"joinTime":"1694481508000","endTime":"1696798800000","remove":false,"rank":2248},{"seasonId":"4zone_3v3_ga2_c3s1_45a","eventInstanceId":"GA2_SEASON_45A:O1696885200000","league":"KYBER","wins":0,"losses":0,"seasonPoints":12458,"division":15,"joinTime":"1696885280000","endTime":"1699218000000","remove":false,"rank":13880},{"seasonId":"4zone_5v5_ga2_c3s1_46a","eventInstanceId":"GA2_SEASON_46A:O1699308000000","league":"KYBER","wins":0,"losses":0,"seasonPoints":4368,"division":15,"joinTime":"1699316380000","endTime":"1701640800000","remove":false,"rank":0}],"playerId":"fLk_aC16RTa6_p-DBmiTLw","playerName":"TheEwokening","playerLevel":85,"memberLevel":4,"guildXp":0,"lastActivityTime":"1699842273000","squadPower":205774,"guildJoinTime":"1631009723","galacticPower":"10106473","playerTitle":"PLAYERTITLE_MARQUEE_PRINCESSKNEESAA","playerPortrait":"PLAYERPORTRAIT_GLVADER","lifetimeSeasonScore":"173562","leagueId":"KYBER","shipGalacticPower":"4193358","characterGalacticPower":"5913115"},{"memberContribution":[{"type":2,"currentValue":"0","lifetimeValue":"390736"},{"type":3,"currentValue":"0","lifetimeValue":"257"},{"type":1,"currentValue":"0","lifetimeValue":"772576"}],"seasonStatus":[{"seasonId":"4zone_5v5_ga2_c3s1_44a","eventInstanceId":"GA2_SEASON_44A:O1694466000000","league":"BRONZIUM","wins":0,"losses":0,"seasonPoints":3261,"division":20,"joinTime":"1694466233000","endTime":"1696798800000","remove":false,"rank":4230},{"seasonId":"4zone_3v3_ga2_c3s1_45a","eventInstanceId":"GA2_SEASON_45A:O1696885200000","league":"BRONZIUM","wins":0,"losses":0,"seasonPoints":3597,"division":20,"joinTime":"1696891850000","endTime":"1699218000000","remove":false,"rank":3322},{"seasonId":"4zone_5v5_ga2_c3s1_46a","eventInstanceId":"GA2_SEASON_46A:O1699308000000","league":"BRONZIUM","wins":0,"losses":0,"seasonPoints":74,"division":25,"joinTime":"1699317380000","endTime":"1701640800000","remove":false,"rank":0}],"playerId":"HSDCiQvUQCmAH_Gk_vK4qg","playerName":"Revned","playerLevel":85,"memberLevel":2,"guildXp":0,"lastActivityTime":"1699834992000","squadPower":177096,"guildJoinTime":"1637555175","galacticPower":"6171743","playerTitle":"PLAYERTITLE_MANDO","playerPortrait":"PLAYERPORTRAIT_MANDO","lifetimeSeasonScore":"215972","leagueId":"BRONZIUM","shipGalacticPower":"2717127","characterGalacticPower":"3454616"},{"memberContribution":[{"type":2,"currentValue":"0","lifetimeValue":"281722"},{"type":3,"currentValue":"0","lifetimeValue":"539"},{"type":1,"currentValue":"0","lifetimeValue":"554127"}],"seasonStatus":[{"seasonId":"4zone_5v5_ga2_c3s1_44a","eventInstanceId":"GA2_SEASON_44A:O1694466000000","league":"BRONZIUM","wins":0,"losses":0,"seasonPoints":2762,"division":15,"joinTime":"1694477887000","endTime":"1696798800000","remove":false,"rank":3002},{"seasonId":"4zone_3v3_ga2_c3s1_45a","eventInstanceId":"GA2_SEASON_45A:O1696885200000","league":"BRONZIUM","wins":0,"losses":0,"seasonPoints":4209,"division":20,"joinTime":"1696902163000","endTime":"1699218000000","remove":false,"rank":7343},{"seasonId":"4zone_5v5_ga2_c3s1_46a","eventInstanceId":"GA2_SEASON_46A:O1699308000000","league":"BRONZIUM","wins":0,"losses":0,"seasonPoints":1524,"division":25,"joinTime":"1699335377000","endTime":"1701640800000","remove":false,"rank":0}],"playerId":"KFbg6YyvTQ6Ltf8c301Jzw","playerName":"BigD","playerLevel":85,"memberLevel":2,"guildXp":0,"lastActivityTime":"1699815529000","squadPower":160061,"guildJoinTime":"1652912139","galacticPower":"6866497","playerTitle":"PLAYERTITLE_GENERAL","playerPortrait":"PLAYERPORTRAIT_TU18_ALL_PLAYERS","lifetimeSeasonScore":"230247","leagueId":"BRONZIUM","shipGalacticPower":"3165344","characterGalacticPower":"3701153"},{"memberContribution":[{"type":2,"currentValue":"0","lifetimeValue":"307678"},{"type":3,"currentValue":"0","lifetimeValue":"423"},{"type":1,"currentValue":"0","lifetimeValue":"576303"}],"seasonStatus":[{"seasonId":"4zone_5v5_ga2_c3s1_44a","eventInstanceId":"GA2_SEASON_44A:O1694466000000","league":"CHROMIUM","wins":0,"losses":0,"seasonPoints":3392,"division":25,"joinTime":"1694466125000","endTime":"1696798800000","remove":false,"rank":6288},{"seasonId":"4zone_3v3_ga2_c3s1_45a","eventInstanceId":"GA2_SEASON_45A:O1696885200000","league":"AURODIUM","wins":0,"losses":0,"seasonPoints":2123,"division":5,"joinTime":"1696894450000","endTime":"1699218000000","remove":false,"rank":6243},{"seasonId":"4zone_5v5_ga2_c3s1_46a","eventInstanceId":"GA2_SEASON_46A:O1699308000000","league":"CHROMIUM","wins":0,"losses":0,"seasonPoints":1266,"division":15,"joinTime":"1699310746000","endTime":"1701640800000","remove":false,"rank":0}],"playerId":"F2HUCDftQ3CubQSGQVW0hw","playerName":"pakpak","playerLevel":85,"memberLevel":2,"guildXp":0,"lastActivityTime":"1699825199000","squadPower":172506,"guildJoinTime":"1655309268","galacticPower":"6010664","playerTitle":"PLAYERTITLE_GRANDARENA_CHALLENGE_GENERALKENOBI","playerPortrait":"PLAYERPORTRAIT_GLKENOBI","lifetimeSeasonScore":"101726","leagueId":"CHROMIUM","shipGalacticPower":"2680574","characterGalacticPower":"3330090"},{"memberContribution":[{"type":2,"currentValue":"0","lifetimeValue":"242284"},{"type":3,"currentValue":"0","lifetimeValue":"64"},{"type":1,"currentValue":"0","lifetimeValue":"468375"}],"seasonStatus":[{"seasonId":"4zone_5v5_ga2_c3s1_44a","eventInstanceId":"GA2_SEASON_44A:O1694466000000","league":"CHROMIUM","wins":0,"losses":0,"seasonPoints":5950,"division":15,"joinTime":"1694498612000","endTime":"1696798800000","remove":false,"rank":1853},{"seasonId":"4zone_3v3_ga2_c3s1_45a","eventInstanceId":"GA2_SEASON_45A:O1696885200000","league":"CHROMIUM","wins":0,"losses":0,"seasonPoints":5591,"division":20,"joinTime":"1696890940000","endTime":"1699218000000","remove":false,"rank":5598},{"seasonId":"4zone_5v5_ga2_c3s1_46a","eventInstanceId":"GA2_SEASON_46A:O1699308000000","league":"CHROMIUM","wins":0,"losses":0,"seasonPoints":2426,"division":25,"joinTime":"1699315200000","endTime":"1701640800000","remove":false,"rank":0}],"playerId":"tzcNCz5kT-qHOm8ZC2k_sw","playerName":"cr19","playerLevel":85,"memberLevel":2,"guildXp":0,"lastActivityTime":"1699830537000","squadPower":159444,"guildJoinTime":"1662915986","galacticPower":"5645240","playerTitle":"PLAYERTITLE_SPICEFREIGHTER","playerPortrait":"PLAYERPORTRAIT_501STCREST","lifetimeSeasonScore":"0","leagueId":"CHROMIUM","shipGalacticPower":"2631570","characterGalacticPower":"3013670"},{"memberContribution":[{"type":2,"currentValue":"0","lifetimeValue":"224494"},{"type":3,"currentValue":"0","lifetimeValue":"56"},{"type":1,"currentValue":"0","lifetimeValue":"427894"}],"seasonStatus":[{"seasonId":"4zone_5v5_ga2_c3s1_44a","eventInstanceId":"GA2_SEASON_44A:O1694466000000","league":"BRONZIUM","wins":0,"losses":0,"seasonPoints":2846,"division":20,"joinTime":"1694493229000","endTime":"1696798800000","remove":false,"rank":10996},{"seasonId":"4zone_3v3_ga2_c3s1_45a","eventInstanceId":"GA2_SEASON_45A:O1696885200000","league":"BRONZIUM","wins":0,"losses":0,"seasonPoints":1584,"division":25,"joinTime":"1696896570000","endTime":"1699218000000","remove":false,"rank":4188},{"seasonId":"4zone_5v5_ga2_c3s1_46a","eventInstanceId":"GA2_SEASON_46A:O1699308000000","league":"CHROMIUM","wins":0,"losses":0,"seasonPoints":1058,"division":10,"joinTime":"1699322480000","endTime":"1701640800000","remove":false,"rank":0}],"playerId":"4ypRauKJS1K8Kw72J0bPiw","playerName":"Xcb","playerLevel":85,"memberLevel":2,"guildXp":0,"lastActivityTime":"1699769226000","squadPower":168829,"guildJoinTime":"1662921120","galacticPower":"4851601","playerTitle":"PLAYERTITLE_GAC_BLUE","playerPortrait":"PLAYERPORTRAIT_POE","lifetimeSeasonScore":"114938","leagueId":"CHROMIUM","shipGalacticPower":"2251366","characterGalacticPower":"2600235"},{"memberContribution":[{"type":2,"currentValue":"564","lifetimeValue":"252498"},{"type":3,"currentValue":"0","lifetimeValue":"32"},{"type":1,"currentValue":"103","lifetimeValue":"494023"}],"seasonStatus":[{"seasonId":"4zone_5v5_ga2_c3s1_44a","eventInstanceId":"GA2_SEASON_44A:O1694466000000","league":"AURODIUM","wins":0,"losses":0,"seasonPoints":6877,"division":15,"joinTime":"1694470981000","endTime":"1696798800000","remove":false,"rank":8258},{"seasonId":"4zone_3v3_ga2_c3s1_45a","eventInstanceId":"GA2_SEASON_45A:O1696885200000","league":"AURODIUM","wins":0,"losses":0,"seasonPoints":8980,"division":15,"joinTime":"1696886239000","endTime":"1699218000000","remove":false,"rank":7513},{"seasonId":"4zone_5v5_ga2_c3s1_46a","eventInstanceId":"GA2_SEASON_46A:O1699308000000","league":"AURODIUM","wins":0,"losses":0,"seasonPoints":2738,"division":20,"joinTime":"1699311735000","endTime":"1701640800000","remove":false,"rank":0}],"playerId":"UKHX4T-bRc2bp2cqaKZbKw","playerName":"Riek","playerLevel":85,"memberLevel":3,"guildXp":0,"lastActivityTime":"1699842120000","squadPower":159867,"guildJoinTime":"1663520954","galacticPower":"7401372","playerTitle":"PLAYERTITLE_501STLEGION","playerPortrait":"PLAYERPORTRAIT_DESTROYER","lifetimeSeasonScore":"0","leagueId":"AURODIUM","shipGalacticPower":"3505219","characterGalacticPower":"3896153"},{"memberContribution":[{"type":2,"currentValue":"0","lifetimeValue":"242146"},{"type":3,"currentValue":"0","lifetimeValue":"320"},{"type":1,"currentValue":"0","lifetimeValue":"461223"}],"seasonStatus":[{"seasonId":"4zone_5v5_ga2_c3s1_44a","eventInstanceId":"GA2_SEASON_44A:O1694466000000","league":"CHROMIUM","wins":0,"losses":0,"seasonPoints":5132,"division":5,"joinTime":"1694476243000","endTime":"1696798800000","remove":false,"rank":12209},{"seasonId":"4zone_3v3_ga2_c3s1_45a","eventInstanceId":"GA2_SEASON_45A:O1696885200000","league":"BRONZIUM","wins":0,"losses":0,"seasonPoints":9424,"division":25,"joinTime":"1696885861000","endTime":"1699218000000","remove":false,"rank":571},{"seasonId":"4zone_5v5_ga2_c3s1_46a","eventInstanceId":"GA2_SEASON_46A:O1699308000000","league":"CHROMIUM","wins":0,"losses":0,"seasonPoints":1428,"division":25,"joinTime":"1699317224000","endTime":"1701640800000","remove":false,"rank":0}],"playerId":"4A0JzHGkRQWyecH4CSawaA","playerName":"Echo 7","playerLevel":85,"memberLevel":2,"guildXp":0,"lastActivityTime":"1699828696000","squadPower":176303,"guildJoinTime":"1663562745","galacticPower":"5726111","playerTitle":"PLAYERTITLE_GLJMLS_QUEST_003","playerPortrait":"PLAYERPORTRAIT_GLLUKE","lifetimeSeasonScore":"41340","leagueId":"CHROMIUM","shipGalacticPower":"2647212","characterGalacticPower":"3078899"},{"memberContribution":[{"type":2,"currentValue":"480","lifetimeValue":"186626"},{"type":3,"currentValue":"0","lifetimeValue":"157"},{"type":1,"currentValue":"0","lifetimeValue":"397238"}],"seasonStatus":[{"seasonId":"4zone_5v5_ga2_c3s1_44a","eventInstanceId":"GA2_SEASON_44A:O1694466000000","league":"CHROMIUM","wins":0,"losses":0,"seasonPoints":2185,"division":10,"joinTime":"1694475914000","endTime":"1696798800000","remove":false,"rank":9819},{"seasonId":"4zone_3v3_ga2_c3s1_45a","eventInstanceId":"GA2_SEASON_45A:O1696885200000","league":"CHROMIUM","wins":0,"losses":0,"seasonPoints":3949,"division":10,"joinTime":"1696886889000","endTime":"1699218000000","remove":false,"rank":8941},{"seasonId":"4zone_5v5_ga2_c3s1_46a","eventInstanceId":"GA2_SEASON_46A:O1699308000000","league":"CHROMIUM","wins":0,"losses":0,"seasonPoints":149,"division":15,"joinTime":"1699313579000","endTime":"1701640800000","remove":false,"rank":0}],"playerId":"Pd-2yynGRtSsl9yzP7_-0A","playerName":"Pigeonesque","playerLevel":85,"memberLevel":3,"guildXp":0,"lastActivityTime":"1699838757000","squadPower":172547,"guildJoinTime":"1664166134","galacticPower":"6520940","playerTitle":"PLAYERTITLE_DOCTORAPHRA","playerPortrait":"PLAYERPORTRAIT_DOCTORAPHRA","lifetimeSeasonScore":"127384","leagueId":"CHROMIUM","shipGalacticPower":"2410395","characterGalacticPower":"4110545"},{"memberContribution":[{"type":2,"currentValue":"444","lifetimeValue":"202936"},{"type":3,"currentValue":"0","lifetimeValue":"0"},{"type":1,"currentValue":"86","lifetimeValue":"356179"}],"seasonStatus":[{"seasonId":"4zone_5v5_ga2_c3s1_44a","eventInstanceId":"GA2_SEASON_44A:O1694466000000","league":"CHROMIUM","wins":0,"losses":0,"seasonPoints":3687,"division":25,"joinTime":"1694471909000","endTime":"1696798800000","remove":false,"rank":1099},{"seasonId":"4zone_3v3_ga2_c3s1_45a","eventInstanceId":"GA2_SEASON_45A:O1696885200000","league":"AURODIUM","wins":0,"losses":0,"seasonPoints":2994,"division":10,"joinTime":"1696894295000","endTime":"1699218000000","remove":false,"rank":370},{"seasonId":"4zone_5v5_ga2_c3s1_46a","eventInstanceId":"GA2_SEASON_46A:O1699308000000","league":"CHROMIUM","wins":0,"losses":0,"seasonPoints":1416,"division":25,"joinTime":"1699318549000","endTime":"1701640800000","remove":false,"rank":0}],"playerId":"EohKQlEFTvyY0bISHqes8A","playerName":"Romp0m8167426","playerLevel":85,"memberLevel":2,"guildXp":0,"lastActivityTime":"1699839017000","squadPower":162902,"guildJoinTime":"1665337907","galacticPower":"6342427","playerTitle":"PLAYERTITLE_GRANDARENA_CHALLENGE_GENERALKENOBI","playerPortrait":"PLAYERPORTRAIT_RANGETROOPER","lifetimeSeasonScore":"198721","leagueId":"CHROMIUM","shipGalacticPower":"2945522","characterGalacticPower":"3396905"},{"memberContribution":[{"type":2,"currentValue":"132","lifetimeValue":"222096"},{"type":3,"currentValue":"0","lifetimeValue":"469"},{"type":1,"currentValue":"86","lifetimeValue":"408861"}],"seasonStatus":[{"seasonId":"4zone_5v5_ga2_c3s1_44a","eventInstanceId":"GA2_SEASON_44A:O1694466000000","league":"KYBER","wins":0,"losses":0,"seasonPoints":9522,"division":15,"joinTime":"1694469887000","endTime":"1696798800000","remove":false,"rank":9010},{"seasonId":"4zone_3v3_ga2_c3s1_45a","eventInstanceId":"GA2_SEASON_45A:O1696885200000","league":"KYBER","wins":0,"losses":0,"seasonPoints":11803,"division":15,"joinTime":"1696888967000","endTime":"1699218000000","remove":false,"rank":4416},{"seasonId":"4zone_5v5_ga2_c3s1_46a","eventInstanceId":"GA2_SEASON_46A:O1699308000000","league":"KYBER","wins":0,"losses":0,"seasonPoints":2831,"division":15,"joinTime":"1699311609000","endTime":"1701640800000","remove":false,"rank":0}],"playerId":"popz6L8zR82ZrUcnJtWCDg","playerName":"ope","playerLevel":85,"memberLevel":2,"guildXp":0,"lastActivityTime":"1699837431000","squadPower":188080,"guildJoinTime":"1665599571","galacticPower":"9683594","playerTitle":"PLAYERTITLE_JEDIKNIGHT","playerPortrait":"PLAYERPORTRAIT_GLLUKE","lifetimeSeasonScore":"737238","leagueId":"KYBER","shipGalacticPower":"3844664","characterGalacticPower":"5838930"},{"memberContribution":[{"type":2,"currentValue":"0","lifetimeValue":"233440"},{"type":3,"currentValue":"0","lifetimeValue":"552"},{"type":1,"currentValue":"0","lifetimeValue":"434232"}],"seasonStatus":[{"seasonId":"4zone_5v5_ga2_c3s1_44a","eventInstanceId":"GA2_SEASON_44A:O1694466000000","league":"KYBER","wins":0,"losses":0,"seasonPoints":8992,"division":15,"joinTime":"1694467280000","endTime":"1696798800000","remove":false,"rank":9745},{"seasonId":"4zone_3v3_ga2_c3s1_45a","eventInstanceId":"GA2_SEASON_45A:O1696885200000","league":"KYBER","wins":0,"losses":0,"seasonPoints":7121,"division":15,"joinTime":"1696885839000","endTime":"1699218000000","remove":false,"rank":11843},{"seasonId":"4zone_5v5_ga2_c3s1_46a","eventInstanceId":"GA2_SEASON_46A:O1699308000000","league":"KYBER","wins":0,"losses":0,"seasonPoints":2030,"division":15,"joinTime":"1699308222000","endTime":"1701640800000","remove":false,"rank":0}],"playerId":"kxTmXANgR9CGxRNe6vJ3Yg","playerName":"DrippingPP","playerLevel":85,"memberLevel":3,"guildXp":0,"lastActivityTime":"1699832662000","squadPower":176634,"guildJoinTime":"1665957446","galacticPower":"9583387","playerTitle":"PLAYERTITLE_LOYAL_FRIEND","playerPortrait":"PLAYERPORTRAIT_THECHOSENONE","lifetimeSeasonScore":"885508","leagueId":"KYBER","shipGalacticPower":"4177120","characterGalacticPower":"5406267"},{"memberContribution":[{"type":2,"currentValue":"0","lifetimeValue":"235200"},{"type":3,"currentValue":"0","lifetimeValue":"108"},{"type":1,"currentValue":"0","lifetimeValue":"422244"}],"seasonStatus":[{"seasonId":"4zone_5v5_ga2_c3s1_44a","eventInstanceId":"GA2_SEASON_44A:O1694466000000","league":"KYBER","wins":0,"losses":0,"seasonPoints":9820,"division":10,"joinTime":"1694476277000","endTime":"1696798800000","remove":false,"rank":8140},{"seasonId":"4zone_3v3_ga2_c3s1_45a","eventInstanceId":"GA2_SEASON_45A:O1696885200000","league":"KYBER","wins":0,"losses":0,"seasonPoints":11489,"division":10,"joinTime":"1696887757000","endTime":"1699218000000","remove":false,"rank":13336},{"seasonId":"4zone_5v5_ga2_c3s1_46a","eventInstanceId":"GA2_SEASON_46A:O1699308000000","league":"KYBER","wins":0,"losses":0,"seasonPoints":2057,"division":15,"joinTime":"1699311153000","endTime":"1701640800000","remove":false,"rank":0}],"playerId":"Vtp73ClyQT6b-obPFGWt1w","playerName":"Gloern","playerLevel":85,"memberLevel":2,"guildXp":0,"lastActivityTime":"1699836167000","squadPower":181810,"guildJoinTime":"1665967418","galacticPower":"9314573","playerTitle":"PLAYERTITLE_GLJABBA_QUEST_003","playerPortrait":"PLAYERPORTRAIT_GLJABBA","lifetimeSeasonScore":"887744","leagueId":"KYBER","shipGalacticPower":"3935470","characterGalacticPower":"5379103"},{"memberContribution":[{"type":2,"currentValue":"0","lifetimeValue":"211214"},{"type":3,"currentValue":"0","lifetimeValue":"45"},{"type":1,"currentValue":"0","lifetimeValue":"388121"}],"seasonStatus":[{"seasonId":"4zone_5v5_ga2_c3s1_44a","eventInstanceId":"GA2_SEASON_44A:O1694466000000","league":"AURODIUM","wins":0,"losses":0,"seasonPoints":10948,"division":20,"joinTime":"1694470099000","endTime":"1696798800000","remove":false,"rank":5136},{"seasonId":"4zone_3v3_ga2_c3s1_45a","eventInstanceId":"GA2_SEASON_45A:O1696885200000","league":"AURODIUM","wins":0,"losses":0,"seasonPoints":5220,"division":15,"joinTime":"1696885248000","endTime":"1699218000000","remove":false,"rank":5321},{"seasonId":"4zone_5v5_ga2_c3s1_46a","eventInstanceId":"GA2_SEASON_46A:O1699308000000","league":"AURODIUM","wins":0,"losses":0,"seasonPoints":2612,"division":15,"joinTime":"1699309123000","endTime":"1701640800000","remove":false,"rank":0}],"playerId":"nXPU78w8QxegccabKHHpJA","playerName":"Frubzy","playerLevel":85,"memberLevel":2,"guildXp":0,"lastActivityTime":"1699840673000","squadPower":173745,"guildJoinTime":"1666585605","galacticPower":"7920490","playerTitle":"PLAYERTITLE_GAC_DIRECTOR","playerPortrait":"PLAYERPORTRAIT_TARKIN","lifetimeSeasonScore":"175556","leagueId":"AURODIUM","shipGalacticPower":"3683114","characterGalacticPower":"4237376"},{"memberContribution":[{"type":2,"currentValue":"0","lifetimeValue":"132062"},{"type":3,"currentValue":"0","lifetimeValue":"425"},{"type":1,"currentValue":"0","lifetimeValue":"336673"}],"seasonStatus":[{"seasonId":"4zone_5v5_ga2_c3s1_44a","eventInstanceId":"GA2_SEASON_44A:O1694466000000","league":"KYBER","wins":0,"losses":0,"seasonPoints":10175,"division":10,"joinTime":"1694478762000","endTime":"1696798800000","remove":false,"rank":12809},{"seasonId":"4zone_3v3_ga2_c3s1_45a","eventInstanceId":"GA2_SEASON_45A:O1696885200000","league":"KYBER","wins":0,"losses":0,"seasonPoints":10813,"division":15,"joinTime":"1696885698000","endTime":"1699218000000","remove":false,"rank":8118},{"seasonId":"4zone_5v5_ga2_c3s1_46a","eventInstanceId":"GA2_SEASON_46A:O1699308000000","league":"KYBER","wins":0,"losses":0,"seasonPoints":4461,"division":15,"joinTime":"1699319080000","endTime":"1701640800000","remove":false,"rank":0}],"playerId":"sK4ZO-rDS1GEw6I6Ek6mVg","playerName":"Nysterio","playerLevel":85,"memberLevel":3,"guildXp":0,"lastActivityTime":"1699842320000","squadPower":197617,"guildJoinTime":"1668364154","galacticPower":"11596790","playerTitle":"PLAYERTITLE_DARKLORD","playerPortrait":"PLAYERPORTRAIT_KYLOMASKED","lifetimeSeasonScore":"481653","leagueId":"KYBER","shipGalacticPower":"4405215","characterGalacticPower":"7191575"},{"memberContribution":[{"type":2,"currentValue":"0","lifetimeValue":"203204"},{"type":3,"currentValue":"0","lifetimeValue":"56"},{"type":1,"currentValue":"0","lifetimeValue":"351086"}],"seasonStatus":[{"seasonId":"4zone_5v5_ga2_c3s1_44a","eventInstanceId":"GA2_SEASON_44A:O1694466000000","league":"CHROMIUM","wins":0,"losses":0,"seasonPoints":9853,"division":25,"joinTime":"1694466634000","endTime":"1696798800000","remove":false,"rank":4647},{"seasonId":"4zone_3v3_ga2_c3s1_45a","eventInstanceId":"GA2_SEASON_45A:O1696885200000","league":"AURODIUM","wins":0,"losses":0,"seasonPoints":7919,"division":15,"joinTime":"1696887895000","endTime":"1699218000000","remove":false,"rank":9337},{"seasonId":"4zone_5v5_ga2_c3s1_46a","eventInstanceId":"GA2_SEASON_46A:O1699308000000","league":"AURODIUM","wins":0,"losses":0,"seasonPoints":2833,"division":15,"joinTime":"1699349192000","endTime":"1701640800000","remove":false,"rank":0}],"playerId":"qiiJ4VkHS4WTk85Qa46s8A","playerName":"Siedmiu","playerLevel":85,"memberLevel":2,"guildXp":0,"lastActivityTime":"1699829034000","squadPower":156309,"guildJoinTime":"1668628525","galacticPower":"7048740","playerTitle":"PLAYERTITLE_SEASON001_KYBER_11PLUS","playerPortrait":"PLAYERPORTRAIT_GIFT_01","lifetimeSeasonScore":"324143","leagueId":"AURODIUM","shipGalacticPower":"2956243","characterGalacticPower":"4092497"},{"memberContribution":[{"type":2,"currentValue":"90","lifetimeValue":"168822"},{"type":3,"currentValue":"0","lifetimeValue":"417"},{"type":1,"currentValue":"86","lifetimeValue":"326661"}],"seasonStatus":[{"seasonId":"4zone_5v5_ga2_c3s1_44a","eventInstanceId":"GA2_SEASON_44A:O1694466000000","league":"AURODIUM","wins":0,"losses":0,"seasonPoints":10051,"division":10,"joinTime":"1694473755000","endTime":"1696798800000","remove":false,"rank":6851},{"seasonId":"4zone_3v3_ga2_c3s1_45a","eventInstanceId":"GA2_SEASON_45A:O1696885200000","league":"AURODIUM","wins":0,"losses":0,"seasonPoints":11007,"division":5,"joinTime":"1696900520000","endTime":"1699218000000","remove":false,"rank":611},{"seasonId":"4zone_5v5_ga2_c3s1_46a","eventInstanceId":"GA2_SEASON_46A:O1699308000000","league":"CHROMIUM","wins":0,"losses":0,"seasonPoints":1400,"division":25,"joinTime":"1699327199000","endTime":"1701640800000","remove":false,"rank":0}],"playerId":"sabFe2nqTsS9AukKD1ffog","playerName":"Murray","playerLevel":85,"memberLevel":2,"guildXp":0,"lastActivityTime":"1699837667000","squadPower":161993,"guildJoinTime":"1669005924","galacticPower":"7156674","playerTitle":"PLAYERTITLE_HEAD_CLANKER","playerPortrait":"PLAYERPORTRAIT_GLKYLOREN","lifetimeSeasonScore":"351672","leagueId":"CHROMIUM","shipGalacticPower":"3155200","characterGalacticPower":"4001474"},{"memberContribution":[{"type":2,"currentValue":"0","lifetimeValue":"160512"},{"type":3,"currentValue":"0","lifetimeValue":"10"},{"type":1,"currentValue":"0","lifetimeValue":"313907"}],"seasonStatus":[{"seasonId":"4zone_5v5_ga2_c3s1_44a","eventInstanceId":"GA2_SEASON_44A:O1694466000000","league":"BRONZIUM","wins":0,"losses":0,"seasonPoints":4710,"division":20,"joinTime":"1694477843000","endTime":"1696798800000","remove":false,"rank":4331},{"seasonId":"4zone_3v3_ga2_c3s1_45a","eventInstanceId":"GA2_SEASON_45A:O1696885200000","league":"BRONZIUM","wins":0,"losses":0,"seasonPoints":7259,"division":25,"joinTime":"1696887609000","endTime":"1699218000000","remove":false,"rank":2451},{"seasonId":"4zone_5v5_ga2_c3s1_46a","eventInstanceId":"GA2_SEASON_46A:O1699308000000","league":"CHROMIUM","wins":0,"losses":0,"seasonPoints":0,"division":10,"joinTime":"1699309536000","endTime":"1701640800000","remove":false,"rank":0}],"playerId":"PQT8M2wcRQKTaydsObpBaw","playerName":"Malan Borthalos","playerLevel":85,"memberLevel":2,"guildXp":0,"lastActivityTime":"1699832620000","squadPower":177290,"guildJoinTime":"1669308496","galacticPower":"5002990","playerTitle":"PLAYERTITLE_GLJMLS_QUEST_002","playerPortrait":"PLAYERPORTRAIT_GLLUKE","lifetimeSeasonScore":"220670","leagueId":"CHROMIUM","shipGalacticPower":"1973414","characterGalacticPower":"3029576"},{"memberContribution":[{"type":2,"currentValue":"0","lifetimeValue":"198172"},{"type":3,"currentValue":"0","lifetimeValue":"302"},{"type":1,"currentValue":"0","lifetimeValue":"323317"}],"seasonStatus":[{"seasonId":"4zone_5v5_ga2_c3s1_44a","eventInstanceId":"GA2_SEASON_44A:O1694466000000","league":"BRONZIUM","wins":0,"losses":0,"seasonPoints":6530,"division":25,"joinTime":"1694470392000","endTime":"1696798800000","remove":false,"rank":424},{"seasonId":"4zone_3v3_ga2_c3s1_45a","eventInstanceId":"GA2_SEASON_45A:O1696885200000","league":"CHROMIUM","wins":0,"losses":0,"seasonPoints":6460,"division":5,"joinTime":"1696892017000","endTime":"1699218000000","remove":false,"rank":1104},{"seasonId":"4zone_5v5_ga2_c3s1_46a","eventInstanceId":"GA2_SEASON_46A:O1699308000000","league":"BRONZIUM","wins":0,"losses":0,"seasonPoints":0,"division":20,"joinTime":"1699412582000","endTime":"1701640800000","remove":false,"rank":0}],"playerId":"07_amVa3R2uAChjynAsURg","playerName":"Tiarnan","playerLevel":85,"memberLevel":2,"guildXp":0,"lastActivityTime":"1699811945000","squadPower":156660,"guildJoinTime":"1670609164","galacticPower":"7251870","playerTitle":"PLAYERTITLE_DARKLORD","playerPortrait":"PLAYERPORTRAIT_JEDI_GENERAL","lifetimeSeasonScore":"34771","leagueId":"BRONZIUM","shipGalacticPower":"3134292","characterGalacticPower":"4117578"},{"memberContribution":[{"type":2,"currentValue":"0","lifetimeValue":"188060"},{"type":3,"currentValue":"0","lifetimeValue":"72"},{"type":1,"currentValue":"0","lifetimeValue":"305341"}],"seasonStatus":[{"seasonId":"4zone_5v5_ga2_c3s1_44a","eventInstanceId":"GA2_SEASON_44A:O1694466000000","league":"CHROMIUM","wins":0,"losses":0,"seasonPoints":6345,"division":25,"joinTime":"1694466589000","endTime":"1696798800000","remove":false,"rank":1025},{"seasonId":"4zone_3v3_ga2_c3s1_45a","eventInstanceId":"GA2_SEASON_45A:O1696885200000","league":"AURODIUM","wins":0,"losses":0,"seasonPoints":3446,"division":10,"joinTime":"1696890129000","endTime":"1699218000000","remove":false,"rank":5256},{"seasonId":"4zone_5v5_ga2_c3s1_46a","eventInstanceId":"GA2_SEASON_46A:O1699308000000","league":"AURODIUM","wins":0,"losses":0,"seasonPoints":1249,"division":10,"joinTime":"1699308001000","endTime":"1701640800000","remove":false,"rank":0}],"playerId":"MCfl7TX1RIyBrFSdgX6cig","playerName":"Kreol","playerLevel":85,"memberLevel":2,"guildXp":0,"lastActivityTime":"1699817652000","squadPower":154570,"guildJoinTime":"1671390858","galacticPower":"6338707","playerTitle":"PLAYERTITLE_DARKSIDEHISTORIAN","playerPortrait":"PLAYERPORTRAIT_WICKET","lifetimeSeasonScore":"1320","leagueId":"AURODIUM","shipGalacticPower":"2784181","characterGalacticPower":"3554526"},{"memberContribution":[{"type":2,"currentValue":"0","lifetimeValue":"151054"},{"type":3,"currentValue":"0","lifetimeValue":"13"},{"type":1,"currentValue":"1986","lifetimeValue":"238241"}],"seasonStatus":[{"seasonId":"4zone_5v5_ga2_c3s1_44a","eventInstanceId":"GA2_SEASON_44A:O1694466000000","league":"AURODIUM","wins":0,"losses":0,"seasonPoints":10162,"division":10,"joinTime":"1694466002000","endTime":"1696798800000","remove":false,"rank":9327},{"seasonId":"4zone_3v3_ga2_c3s1_45a","eventInstanceId":"GA2_SEASON_45A:O1696885200000","league":"AURODIUM","wins":0,"losses":0,"seasonPoints":9230,"division":5,"joinTime":"1696889723000","endTime":"1699218000000","remove":false,"rank":2800},{"seasonId":"4zone_5v5_ga2_c3s1_46a","eventInstanceId":"GA2_SEASON_46A:O1699308000000","league":"CHROMIUM","wins":0,"losses":0,"seasonPoints":3751,"division":20,"joinTime":"1699312172000","endTime":"1701640800000","remove":false,"rank":0}],"playerId":"R6STBBR9SZSsuKevEmhX0w","playerName":"The5thEmperor","playerLevel":85,"memberLevel":2,"guildXp":0,"lastActivityTime":"1699839847000","squadPower":162391,"guildJoinTime":"1675020226","galacticPower":"6660222","playerTitle":"PLAYERTITLE_DARKLORD","playerPortrait":"PLAYERPORTRAIT_GLKYLOREN","lifetimeSeasonScore":"160554","leagueId":"CHROMIUM","shipGalacticPower":"2835268","characterGalacticPower":"3824954"},{"memberContribution":[{"type":2,"currentValue":"600","lifetimeValue":"133350"},{"type":3,"currentValue":"0","lifetimeValue":"160"},{"type":1,"currentValue":"96","lifetimeValue":"214007"}],"seasonStatus":[{"seasonId":"4zone_5v5_ga2_c3s1_44a","eventInstanceId":"GA2_SEASON_44A:O1694466000000","league":"AURODIUM","wins":0,"losses":0,"seasonPoints":8219,"division":10,"joinTime":"1694468648000","endTime":"1696798800000","remove":false,"rank":2335},{"seasonId":"4zone_3v3_ga2_c3s1_45a","eventInstanceId":"GA2_SEASON_45A:O1696885200000","league":"AURODIUM","wins":0,"losses":0,"seasonPoints":10090,"division":10,"joinTime":"1696888144000","endTime":"1699218000000","remove":false,"rank":6019},{"seasonId":"4zone_5v5_ga2_c3s1_46a","eventInstanceId":"GA2_SEASON_46A:O1699308000000","league":"AURODIUM","wins":0,"losses":0,"seasonPoints":2114,"division":10,"joinTime":"1699315508000","endTime":"1701640800000","remove":false,"rank":0}],"playerId":"fhXnxhBSTgC-TjfvjuFDoQ","playerName":"Uncle Buttery","playerLevel":85,"memberLevel":3,"guildXp":0,"lastActivityTime":"1699841866000","squadPower":180429,"guildJoinTime":"1675038744","galacticPower":"7029606","playerTitle":"PLAYERTITLE_GRANDARENA_CHALLENGE_GENERALKENOBI","playerPortrait":"PLAYERPORTRAIT_GLKENOBI","lifetimeSeasonScore":"292517","leagueId":"AURODIUM","shipGalacticPower":"3014390","characterGalacticPower":"4015216"},{"memberContribution":[{"type":2,"currentValue":"320","lifetimeValue":"123078"},{"type":3,"currentValue":"0","lifetimeValue":"34"},{"type":1,"currentValue":"96","lifetimeValue":"170517"}],"seasonStatus":[{"seasonId":"4zone_5v5_ga2_c3s1_44a","eventInstanceId":"GA2_SEASON_44A:O1694466000000","league":"CHROMIUM","wins":0,"losses":0,"seasonPoints":5215,"division":5,"joinTime":"1694472790000","endTime":"1696798800000","remove":false,"rank":11685},{"seasonId":"4zone_3v3_ga2_c3s1_45a","eventInstanceId":"GA2_SEASON_45A:O1696885200000","league":"BRONZIUM","wins":0,"losses":0,"seasonPoints":7785,"division":25,"joinTime":"1696888183000","endTime":"1699218000000","remove":false,"rank":5477},{"seasonId":"4zone_5v5_ga2_c3s1_46a","eventInstanceId":"GA2_SEASON_46A:O1699308000000","league":"CHROMIUM","wins":0,"losses":0,"seasonPoints":1270,"division":15,"joinTime":"1699317001000","endTime":"1701640800000","remove":false,"rank":0}],"playerId":"1R1psHy0RP2iZI9ZXu5HSQ","playerName":"saintskywalker","playerLevel":85,"memberLevel":2,"guildXp":0,"lastActivityTime":"1699842341000","squadPower":168873,"guildJoinTime":"1678316389","galacticPower":"5427960","playerTitle":"PLAYERTITLE_BETTERGENERAL","playerPortrait":"PLAYERPORTRAIT_GLJABBA","lifetimeSeasonScore":"118616","leagueId":"CHROMIUM","shipGalacticPower":"2220447","characterGalacticPower":"3207513"},{"memberContribution":[{"type":2,"currentValue":"0","lifetimeValue":"103198"},{"type":3,"currentValue":"0","lifetimeValue":"16"},{"type":1,"currentValue":"86","lifetimeValue":"166994"}],"seasonStatus":[{"seasonId":"4zone_5v5_ga2_c3s1_44a","eventInstanceId":"GA2_SEASON_44A:O1694466000000","league":"CHROMIUM","wins":0,"losses":0,"seasonPoints":2082,"division":15,"joinTime":"1694543017000","endTime":"1696798800000","remove":false,"rank":6835},{"seasonId":"4zone_3v3_ga2_c3s1_45a","eventInstanceId":"GA2_SEASON_45A:O1696885200000","league":"CHROMIUM","wins":0,"losses":0,"seasonPoints":7548,"division":15,"joinTime":"1696911427000","endTime":"1699218000000","remove":false,"rank":573},{"seasonId":"4zone_5v5_ga2_c3s1_46a","eventInstanceId":"GA2_SEASON_46A:O1699308000000","league":"CHROMIUM","wins":0,"losses":0,"seasonPoints":2103,"division":20,"joinTime":"1699319283000","endTime":"1701640800000","remove":false,"rank":0}],"playerId":"BrndPhdbQkantE4-niUoOA","playerName":"Koolbe","playerLevel":85,"memberLevel":3,"guildXp":0,"lastActivityTime":"1699840955000","squadPower":167515,"guildJoinTime":"1678331280","galacticPower":"6615755","playerTitle":"PLAYERTITLE_MARQUEE_MERRIN","playerPortrait":"PLAYERPORTRAIT_MERRIN","lifetimeSeasonScore":"215810","leagueId":"CHROMIUM","shipGalacticPower":"2913434","characterGalacticPower":"3702321"},{"memberContribution":[{"type":2,"currentValue":"0","lifetimeValue":"144254"},{"type":3,"currentValue":"0","lifetimeValue":"142"},{"type":1,"currentValue":"0","lifetimeValue":"199768"}],"seasonStatus":[{"seasonId":"4zone_5v5_ga2_c3s1_44a","eventInstanceId":"GA2_SEASON_44A:O1694466000000","league":"AURODIUM","wins":0,"losses":0,"seasonPoints":10830,"division":25,"joinTime":"1694467064000","endTime":"1696798800000","remove":false,"rank":2764},{"seasonId":"4zone_3v3_ga2_c3s1_45a","eventInstanceId":"GA2_SEASON_45A:O1696885200000","league":"KYBER","wins":0,"losses":0,"seasonPoints":11745,"division":15,"joinTime":"1696885443000","endTime":"1699218000000","remove":false,"rank":9779},{"seasonId":"4zone_5v5_ga2_c3s1_46a","eventInstanceId":"GA2_SEASON_46A:O1699308000000","league":"KYBER","wins":0,"losses":0,"seasonPoints":1636,"division":15,"joinTime":"1699309926000","endTime":"1701640800000","remove":false,"rank":0}],"playerId":"WLBGecQqSUq6R6ngd8p0GQ","playerName":"DarthJarJar","playerLevel":85,"memberLevel":3,"guildXp":0,"lastActivityTime":"1699834131000","squadPower":176543,"guildJoinTime":"1678905164","galacticPower":"6740760","playerTitle":"PLAYERTITLE_HEAD_CLANKER","playerPortrait":"PLAYERPORTRAIT_FIRSTORDER_TIE","lifetimeSeasonScore":"112747","leagueId":"KYBER","shipGalacticPower":"2970879","characterGalacticPower":"3769881"},{"memberContribution":[{"type":2,"currentValue":"152","lifetimeValue":"132846"},{"type":3,"currentValue":"1","lifetimeValue":"180"},{"type":1,"currentValue":"86","lifetimeValue":"175984"}],"seasonStatus":[{"seasonId":"4zone_5v5_ga2_c3s1_44a","eventInstanceId":"GA2_SEASON_44A:O1694466000000","league":"AURODIUM","wins":0,"losses":0,"seasonPoints":545,"division":10,"joinTime":"1694480983000","endTime":"1696798800000","remove":false,"rank":3557},{"seasonId":"4zone_3v3_ga2_c3s1_45a","eventInstanceId":"GA2_SEASON_45A:O1696885200000","league":"AURODIUM","wins":0,"losses":0,"seasonPoints":1977,"division":5,"joinTime":"1696901507000","endTime":"1699218000000","remove":false,"rank":9572},{"seasonId":"4zone_5v5_ga2_c3s1_46a","eventInstanceId":"GA2_SEASON_46A:O1699308000000","league":"CHROMIUM","wins":0,"losses":0,"seasonPoints":470,"division":20,"joinTime":"1699320106000","endTime":"1701640800000","remove":false,"rank":0}],"playerId":"KjFXXhUTQ-i6fGZtNE6g9g","playerName":"Kuskus","playerLevel":85,"memberLevel":2,"guildXp":0,"lastActivityTime":"1699842346000","squadPower":188799,"guildJoinTime":"1678929572","galacticPower":"6349384","playerTitle":"PLAYERTITLE_SEASON001_CARBONITE_ALL","playerPortrait":"PLAYERPORTRAIT_GLPALP","lifetimeSeasonScore":"0","leagueId":"CHROMIUM","shipGalacticPower":"2645985","characterGalacticPower":"3703399"},{"memberContribution":[{"type":2,"currentValue":"0","lifetimeValue":"125168"},{"type":3,"currentValue":"0","lifetimeValue":"8"},{"type":1,"currentValue":"0","lifetimeValue":"151933"}],"seasonStatus":[{"seasonId":"4zone_5v5_ga2_c3s1_44a","eventInstanceId":"GA2_SEASON_44A:O1694466000000","league":"AURODIUM","wins":0,"losses":0,"seasonPoints":4101,"division":10,"joinTime":"1694466211000","endTime":"1696798800000","remove":false,"rank":8974},{"seasonId":"4zone_3v3_ga2_c3s1_45a","eventInstanceId":"GA2_SEASON_45A:O1696885200000","league":"AURODIUM","wins":0,"losses":0,"seasonPoints":5136,"division":10,"joinTime":"1696889818000","endTime":"1699218000000","remove":false,"rank":4044},{"seasonId":"4zone_5v5_ga2_c3s1_46a","eventInstanceId":"GA2_SEASON_46A:O1699308000000","league":"AURODIUM","wins":0,"losses":0,"seasonPoints":932,"division":10,"joinTime":"1699314631000","endTime":"1701640800000","remove":false,"rank":0}],"playerId":"gY_OsCQSROqDLdtY1SAxDQ","playerName":"Amiss","playerLevel":85,"memberLevel":2,"guildXp":0,"lastActivityTime":"1699813435000","squadPower":170186,"guildJoinTime":"1679245903","galacticPower":"6086105","playerTitle":"PLAYERTITLE_GAC_THEALGORITHM","playerPortrait":"PLAYERPORTRAIT_THECHOSENONE","lifetimeSeasonScore":"489292","leagueId":"AURODIUM","shipGalacticPower":"2692073","characterGalacticPower":"3394032"},{"memberContribution":[{"type":2,"currentValue":"0","lifetimeValue":"95360"},{"type":3,"currentValue":"0","lifetimeValue":"44"},{"type":1,"currentValue":"0","lifetimeValue":"94926"}],"seasonStatus":[{"seasonId":"4zone_5v5_ga2_c3s1_44a","eventInstanceId":"GA2_SEASON_44A:O1694466000000","league":"CHROMIUM","wins":0,"losses":0,"seasonPoints":3461,"division":5,"joinTime":"1694495372000","endTime":"1696798800000","remove":false,"rank":5629},{"seasonId":"4zone_3v3_ga2_c3s1_45a","eventInstanceId":"GA2_SEASON_45A:O1696885200000","league":"BRONZIUM","wins":0,"losses":0,"seasonPoints":5760,"division":20,"joinTime":"1696915209000","endTime":"1699218000000","remove":false,"rank":4209},{"seasonId":"4zone_5v5_ga2_c3s1_46a","eventInstanceId":"GA2_SEASON_46A:O1699308000000","league":"BRONZIUM","wins":0,"losses":0,"seasonPoints":954,"division":25,"joinTime":"1699337558000","endTime":"1701640800000","remove":false,"rank":0}],"playerId":"TaTi1XjJTAiUEdBxi6MI8g","playerName":"Brobi Wan","playerLevel":85,"memberLevel":2,"guildXp":0,"lastActivityTime":"1699834959000","squadPower":182810,"guildJoinTime":"1682875194","galacticPower":"6062717","playerTitle":"PLAYERTITLE_GRANDARENA_CHALLENGE_GENERALKENOBI","playerPortrait":"PLAYERPORTRAIT_GLKENOBI","lifetimeSeasonScore":"245488","leagueId":"BRONZIUM","shipGalacticPower":"2238878","characterGalacticPower":"3823839"},{"memberContribution":[{"type":2,"currentValue":"128","lifetimeValue":"87388"},{"type":3,"currentValue":"0","lifetimeValue":"7"},{"type":1,"currentValue":"86","lifetimeValue":"92175"}],"seasonStatus":[{"seasonId":"4zone_5v5_ga2_c3s1_44a","eventInstanceId":"GA2_SEASON_44A:O1694466000000","league":"BRONZIUM","wins":0,"losses":0,"seasonPoints":7829,"division":25,"joinTime":"1694470690000","endTime":"1696798800000","remove":false,"rank":21},{"seasonId":"4zone_3v3_ga2_c3s1_45a","eventInstanceId":"GA2_SEASON_45A:O1696885200000","league":"CHROMIUM","wins":0,"losses":0,"seasonPoints":10267,"division":10,"joinTime":"1696904707000","endTime":"1699218000000","remove":false,"rank":8118},{"seasonId":"4zone_5v5_ga2_c3s1_46a","eventInstanceId":"GA2_SEASON_46A:O1699308000000","league":"CHROMIUM","wins":0,"losses":0,"seasonPoints":1718,"division":15,"joinTime":"1699316424000","endTime":"1701640800000","remove":false,"rank":0}],"playerId":"sSxiZOAeSyagJWDTmFZpiA","playerName":"Yhwach","playerLevel":85,"memberLevel":2,"guildXp":0,"lastActivityTime":"1699842315000","squadPower":159642,"guildJoinTime":"1684104459","galacticPower":"6312044","playerTitle":"PLAYERTITLE_PRODIGALKNIGHT","playerPortrait":"PLAYERPORTRAIT_DARTHREVAN","lifetimeSeasonScore":"44931","leagueId":"CHROMIUM","shipGalacticPower":"2823186","characterGalacticPower":"3488858"},{"memberContribution":[{"type":2,"currentValue":"0","lifetimeValue":"76068"},{"type":3,"currentValue":"0","lifetimeValue":"108"},{"type":1,"currentValue":"0","lifetimeValue":"70587"}],"seasonStatus":[{"seasonId":"4zone_5v5_ga2_c3s1_44a","eventInstanceId":"GA2_SEASON_44A:O1694466000000","league":"BRONZIUM","wins":0,"losses":0,"seasonPoints":4621,"division":15,"joinTime":"1694468744000","endTime":"1696798800000","remove":false,"rank":3158},{"seasonId":"4zone_3v3_ga2_c3s1_45a","eventInstanceId":"GA2_SEASON_45A:O1696885200000","league":"BRONZIUM","wins":0,"losses":0,"seasonPoints":5046,"division":15,"joinTime":"1696886155000","endTime":"1699218000000","remove":false,"rank":11304},{"seasonId":"4zone_5v5_ga2_c3s1_46a","eventInstanceId":"GA2_SEASON_46A:O1699308000000","league":"BRONZIUM","wins":0,"losses":0,"seasonPoints":1667,"division":20,"joinTime":"1699309436000","endTime":"1701640800000","remove":false,"rank":0}],"playerId":"PGNaoCqVTGC-fRz-02kbNw","playerName":"Fessk","playerLevel":85,"memberLevel":2,"guildXp":0,"lastActivityTime":"1699834405000","squadPower":161492,"guildJoinTime":"1688688183","galacticPower":"5815080","playerTitle":"PLAYERTITLE_ORDER_OF_INQUISITORS","playerPortrait":"PLAYERPORTRAIT_INQUISITOR_BADGE","lifetimeSeasonScore":"0","leagueId":"BRONZIUM","shipGalacticPower":"2693216","characterGalacticPower":"3121864"},{"memberContribution":[{"type":2,"currentValue":"0","lifetimeValue":"36930"},{"type":3,"currentValue":"0","lifetimeValue":"0"},{"type":1,"currentValue":"0","lifetimeValue":"37782"}],"seasonStatus":[{"seasonId":"4zone_5v5_ga2_c3s1_44a","eventInstanceId":"GA2_SEASON_44A:O1694466000000","league":"AURODIUM","wins":0,"losses":0,"seasonPoints":3998,"division":10,"joinTime":"1694472674000","endTime":"1696798800000","remove":false,"rank":9808},{"seasonId":"4zone_3v3_ga2_c3s1_45a","eventInstanceId":"GA2_SEASON_45A:O1696885200000","league":"AURODIUM","wins":0,"losses":0,"seasonPoints":2437,"division":10,"joinTime":"1696899126000","endTime":"1699218000000","remove":false,"rank":6028},{"seasonId":"4zone_5v5_ga2_c3s1_46a","eventInstanceId":"GA2_SEASON_46A:O1699308000000","league":"AURODIUM","wins":0,"losses":0,"seasonPoints":729,"division":5,"joinTime":"1699371664000","endTime":"1701640800000","remove":false,"rank":0}],"playerId":"VRx1420CRga55ZVHVR5WNw","playerName":"Bulldawg","playerLevel":85,"memberLevel":2,"guildXp":0,"lastActivityTime":"1699810973000","squadPower":167451,"guildJoinTime":"1693170825","galacticPower":"7397049","playerTitle":"PLAYERTITLE_GENERALOFTHE501ST","playerPortrait":"PLAYERPORTRAIT_501STCREST","lifetimeSeasonScore":"75631","leagueId":"AURODIUM","shipGalacticPower":"3483835","characterGalacticPower":"3913214"},{"memberContribution":[{"type":2,"currentValue":"0","lifetimeValue":"29638"},{"type":3,"currentValue":"0","lifetimeValue":"0"},{"type":1,"currentValue":"0","lifetimeValue":"37131"}],"seasonStatus":[{"seasonId":"4zone_5v5_ga2_c3s1_44a","eventInstanceId":"GA2_SEASON_44A:O1694466000000","league":"AURODIUM","wins":0,"losses":0,"seasonPoints":4305,"division":5,"joinTime":"1694471741000","endTime":"1696798800000","remove":false,"rank":5585},{"seasonId":"4zone_3v3_ga2_c3s1_45a","eventInstanceId":"GA2_SEASON_45A:O1696885200000","league":"CHROMIUM","wins":0,"losses":0,"seasonPoints":4877,"division":15,"joinTime":"1696898082000","endTime":"1699218000000","remove":false,"rank":1406},{"seasonId":"4zone_5v5_ga2_c3s1_46a","eventInstanceId":"GA2_SEASON_46A:O1699308000000","league":"CHROMIUM","wins":0,"losses":0,"seasonPoints":0,"division":15,"joinTime":"1699371538000","endTime":"1701640800000","remove":false,"rank":0}],"playerId":"NacP9Li7R1ylyCShyt27IA","playerName":"Pitbull","playerLevel":85,"memberLevel":2,"guildXp":0,"lastActivityTime":"1699819520000","squadPower":159660,"guildJoinTime":"1693170826","galacticPower":"6377743","playerTitle":"PLAYERTITLE_GLSLKR_QUEST_001","playerPortrait":"PLAYERPORTRAIT_GLKYLOREN","lifetimeSeasonScore":"136958","leagueId":"CHROMIUM","shipGalacticPower":"2902764","characterGalacticPower":"3474979"},{"memberContribution":[{"type":2,"currentValue":"436","lifetimeValue":"36564"},{"type":3,"currentValue":"0","lifetimeValue":"3"},{"type":1,"currentValue":"86","lifetimeValue":"34906"}],"seasonStatus":[{"seasonId":"4zone_5v5_ga2_c3s1_44a","eventInstanceId":"GA2_SEASON_44A:O1694466000000","league":"BRONZIUM","wins":0,"losses":0,"seasonPoints":7208,"division":25,"joinTime":"1694482850000","endTime":"1696798800000","remove":false,"rank":745},{"seasonId":"4zone_3v3_ga2_c3s1_45a","eventInstanceId":"GA2_SEASON_45A:O1696885200000","league":"CHROMIUM","wins":0,"losses":0,"seasonPoints":4557,"division":10,"joinTime":"1696899225000","endTime":"1699218000000","remove":false,"rank":11226},{"seasonId":"4zone_5v5_ga2_c3s1_46a","eventInstanceId":"GA2_SEASON_46A:O1699308000000","league":"CHROMIUM","wins":0,"losses":0,"seasonPoints":1820,"division":10,"joinTime":"1699323630000","endTime":"1701640800000","remove":false,"rank":0}],"playerId":"tEbBRgbwSbaVgv8tumEzCA","playerName":"BenSwoloOnDBOL","playerLevel":85,"memberLevel":2,"guildXp":0,"lastActivityTime":"1699840890000","squadPower":132315,"guildJoinTime":"1694366618","galacticPower":"5324050","playerTitle":"PLAYERTITLE_SITHSMITER","playerPortrait":"PLAYERPORTRAIT_JEDI_GENERAL","lifetimeSeasonScore":"0","leagueId":"CHROMIUM","shipGalacticPower":"2473796","characterGalacticPower":"2850254"},{"memberContribution":[{"type":2,"currentValue":"562","lifetimeValue":"3002"},{"type":3,"currentValue":"0","lifetimeValue":"3"},{"type":1,"currentValue":"103","lifetimeValue":"3231"}],"seasonStatus":[{"seasonId":"4zone_5v5_ga2_c3s1_44a","eventInstanceId":"GA2_SEASON_44A:O1694466000000","league":"BRONZIUM","wins":0,"losses":0,"seasonPoints":4183,"division":20,"joinTime":"1694469613000","endTime":"1696798800000","remove":false,"rank":4038},{"seasonId":"4zone_3v3_ga2_c3s1_45a","eventInstanceId":"GA2_SEASON_45A:O1696885200000","league":"BRONZIUM","wins":0,"losses":0,"seasonPoints":4672,"division":25,"joinTime":"1696886962000","endTime":"1699218000000","remove":false,"rank":5701},{"seasonId":"4zone_5v5_ga2_c3s1_46a","eventInstanceId":"GA2_SEASON_46A:O1699308000000","league":"CHROMIUM","wins":0,"losses":0,"seasonPoints":145,"division":20,"joinTime":"1699308297000","endTime":"1701640800000","remove":false,"rank":0}],"playerId":"rOgElDStSKWA-Qdlgtab_g","playerName":"Meetra","playerLevel":85,"memberLevel":2,"guildXp":0,"lastActivityTime":"1699842078000","squadPower":158554,"guildJoinTime":"1699488785","galacticPower":"5741944","playerTitle":"PLAYERTITLE_JEDIKNIGHT","playerPortrait":"PLAYERPORTRAIT_BASTILA","lifetimeSeasonScore":"0","leagueId":"CHROMIUM","shipGalacticPower":"2679275","characterGalacticPower":"3062669"},{"memberContribution":[{"type":2,"currentValue":"194","lifetimeValue":"2594"},{"type":3,"currentValue":"0","lifetimeValue":"3"},{"type":1,"currentValue":"86","lifetimeValue":"2292"}],"seasonStatus":[{"seasonId":"4zone_5v5_ga2_c3s1_44a","eventInstanceId":"GA2_SEASON_44A:O1694466000000","league":"CHROMIUM","wins":0,"losses":0,"seasonPoints":4182,"division":5,"joinTime":"1694466023000","endTime":"1696798800000","remove":false,"rank":11455},{"seasonId":"4zone_3v3_ga2_c3s1_45a","eventInstanceId":"GA2_SEASON_45A:O1696885200000","league":"BRONZIUM","wins":0,"losses":0,"seasonPoints":5770,"division":25,"joinTime":"1696900450000","endTime":"1699218000000","remove":false,"rank":4434},{"seasonId":"4zone_5v5_ga2_c3s1_46a","eventInstanceId":"GA2_SEASON_46A:O1699308000000","league":"CHROMIUM","wins":0,"losses":0,"seasonPoints":2274,"division":15,"joinTime":"1699325426000","endTime":"1701640800000","remove":false,"rank":0}],"playerId":"QcIBYXHgRRybnoN8rRr0BA","playerName":"Blue USM","playerLevel":85,"memberLevel":2,"guildXp":0,"lastActivityTime":"1699841479000","squadPower":142902,"guildJoinTime":"1699490662","galacticPower":"4076590","playerTitle":"PLAYERTITLE_SEASON001_KYBER_RANK02_10","playerPortrait":"PLAYERPORTRAIT_GRANDARENA_CHALLENGE_DARTHTRAYA","lifetimeSeasonScore":"163352","leagueId":"CHROMIUM","shipGalacticPower":"1678268","characterGalacticPower":"2398322"}],"inviteStatus":[],"raidStatus":[],"raidResult":[],"territoryBattleStatus":[],"guildEvents":[],"territoryBattleResult":[],"territoryWarStatus":[],"roomAvailable":[],"stat":[],"recentRaidResult":[{"raidMember":[{"playerId":"YAhQkWmDTU2wKDAW42WYLQ","memberProgress":"1052200","memberRank":16,"memberAttempt":0},{"playerId":"1XWZqKsnT-C8qNWSk7mhqA","memberProgress":"0","memberRank":48,"memberAttempt":0},{"playerId":"R6ldSBtLR2aVqWtSPbFfpg","memberProgress":"806899","memberRank":20,"memberAttempt":0},{"playerId":"n8Px3_P4RnG6Z9RNpoKSVw","memberProgress":"104940","memberRank":40,"memberAttempt":0},{"playerId":"fhXnxhBSTgC-TjfvjuFDoQ","memberProgress":"532216","memberRank":28,"memberAttempt":0},{"playerId":"KFbg6YyvTQ6Ltf8c301Jzw","memberProgress":"450000","memberRank":32,"memberAttempt":0},{"playerId":"tzcNCz5kT-qHOm8ZC2k_sw","memberProgress":"178119","memberRank":38,"memberAttempt":0},{"playerId":"WLBGecQqSUq6R6ngd8p0GQ","memberProgress":"3267124","memberRank":3,"memberAttempt":0},{"playerId":"ozpL5CKcRe-9HcECTxP3DQ","memberProgress":"431081","memberRank":33,"memberAttempt":0},{"playerId":"HSDCiQvUQCmAH_Gk_vK4qg","memberProgress":"624599","memberRank":24,"memberAttempt":0},{"playerId":"4A0JzHGkRQWyecH4CSawaA","memberProgress":"759009","memberRank":21,"memberAttempt":0},{"playerId":"PQT8M2wcRQKTaydsObpBaw","memberProgress":"150039","memberRank":39,"memberAttempt":0},{"playerId":"UKHX4T-bRc2bp2cqaKZbKw","memberProgress":"887342","memberRank":18,"memberAttempt":0},{"playerId":"Vtp73ClyQT6b-obPFGWt1w","memberProgress":"2230053","memberRank":5,"memberAttempt":0},{"playerId":"sabFe2nqTsS9AukKD1ffog","memberProgress":"612448","memberRank":25,"memberAttempt":0},{"playerId":"fLk_aC16RTa6_p-DBmiTLw","memberProgress":"4356186","memberRank":1,"memberAttempt":0},{"playerId":"nXPU78w8QxegccabKHHpJA","memberProgress":"1098137","memberRank":13,"memberAttempt":0},{"playerId":"hakEMBtaTqqFoXPldV3UIg","memberProgress":"178920","memberRank":37,"memberAttempt":0},{"playerId":"YkPMDjVVRW6bahLoyWAoLg","memberProgress":"1278051","memberRank":7,"memberAttempt":0},{"playerId":"1R1psHy0RP2iZI9ZXu5HSQ","memberProgress":"0","memberRank":46,"memberAttempt":0},{"playerId":"sK4ZO-rDS1GEw6I6Ek6mVg","memberProgress":"3553634","memberRank":2,"memberAttempt":0},{"playerId":"tEbBRgbwSbaVgv8tumEzCA","memberProgress":"70275","memberRank":41,"memberAttempt":0},{"playerId":"KjFXXhUTQ-i6fGZtNE6g9g","memberProgress":"499514","memberRank":29,"memberAttempt":0},{"playerId":"C-XlXEPHQcO6ugoZGaNvyQ","memberProgress":"1096728","memberRank":14,"memberAttempt":0},{"playerId":"gY_OsCQSROqDLdtY1SAxDQ","memberProgress":"55166","memberRank":42,"memberAttempt":0},{"playerId":"6cFRV0H5Ro2ME9vLZg3Lug","memberProgress":"267281","memberRank":34,"memberAttempt":0},{"playerId":"PGNaoCqVTGC-fRz-02kbNw","memberProgress":"566712","memberRank":27,"memberAttempt":0},{"playerId":"07_amVa3R2uAChjynAsURg","memberProgress":"1127888","memberRank":12,"memberAttempt":0},{"playerId":"-RJCmgceSQCOZECssc_Tzg","memberProgress":"1196455","memberRank":9,"memberAttempt":0},{"playerId":"Pd-2yynGRtSsl9yzP7_-0A","memberProgress":"832435","memberRank":19,"memberAttempt":0},{"playerId":"4ypRauKJS1K8Kw72J0bPiw","memberProgress":"0","memberRank":43,"memberAttempt":0},{"playerId":"BrndPhdbQkantE4-niUoOA","memberProgress":"0","memberRank":45,"memberAttempt":0},{"playerId":"FOo6YGN8QjC2fjgKQC4lFQ","memberProgress":"450000","memberRank":30,"memberAttempt":0},{"playerId":"kxTmXANgR9CGxRNe6vJ3Yg","memberProgress":"2513735","memberRank":4,"memberAttempt":0},{"playerId":"vOlHHoAKQLOluUUMh_GsCw","memberProgress":"1216051","memberRank":8,"memberAttempt":0},{"playerId":"89WBsfisSRWMfs1v-hQ2gg","memberProgress":"1020377","memberRank":17,"memberAttempt":0},{"playerId":"R6STBBR9SZSsuKevEmhX0w","memberProgress":"686063","memberRank":22,"memberAttempt":0},{"playerId":"sSxiZOAeSyagJWDTmFZpiA","memberProgress":"646375","memberRank":23,"memberAttempt":0},{"playerId":"qiiJ4VkHS4WTk85Qa46s8A","memberProgress":"1968529","memberRank":6,"memberAttempt":0},{"playerId":"F2HUCDftQ3CubQSGQVW0hw","memberProgress":"600000","memberRank":26,"memberAttempt":0},{"playerId":"TaTi1XjJTAiUEdBxi6MI8g","memberProgress":"1091396","memberRank":15,"memberAttempt":0},{"playerId":"Dvt29c9pRt2i9hzt8hw2Ew","memberProgress":"0","memberRank":47,"memberAttempt":0},{"playerId":"MCfl7TX1RIyBrFSdgX6cig","memberProgress":"1166104","memberRank":10,"memberAttempt":0},{"playerId":"popz6L8zR82ZrUcnJtWCDg","memberProgress":"1158712","memberRank":11,"memberAttempt":0},{"playerId":"VRx1420CRga55ZVHVR5WNw","memberProgress":"179271","memberRank":36,"memberAttempt":0},{"playerId":"NacP9Li7R1ylyCShyt27IA","memberProgress":"179352","memberRank":35,"memberAttempt":0},{"playerId":"_7jEuSqeRpy4kADdLvAS4w","memberProgress":"0","memberRank":44,"memberAttempt":0},{"playerId":"EohKQlEFTvyY0bISHqes8A","memberProgress":"450000","memberRank":31,"memberAttempt":0}],"encounterProgress":[],"raidId":"kraytdragon","identifier":{"campaignId":"GUILD","campaignMapId":"RAIDS","campaignNodeId":"KRAYTDRAGON","campaignNodeDifficulty":4,"campaignMissionId":"DIFF01"},"duration":"255687","progress":1,"endTime":"1699835610","outcome":1,"guildRewardScore":"41589416","cachedRewards":null}],"recentTerritoryWarResult":[{"territoryWarId":"tw01C","score":"21411","power":314811412,"opponentScore":"22861","endTimeSeconds":"1697389205"},{"territoryWarId":"tw01C","score":"21874","power":300473170,"opponentScore":"11398","endTimeSeconds":"1696179638"},{"territoryWarId":"tw01D","score":"19003","power":322302428,"opponentScore":"18816","endTimeSeconds":"1699470000"},{"territoryWarId":"tw01D","score":"21675","power":319190155,"opponentScore":"22780","endTimeSeconds":"1697047201"},{"territoryWarId":"tw01D","score":"22954","power":327072861,"opponentScore":"12816","endTimeSeconds":"1698256800"},{"territoryWarId":"tw01B","score":"21012","power":304216467,"opponentScore":"14822","endTimeSeconds":"1695837616"},{"territoryWarId":"tw01C","score":"23789","power":334548404,"opponentScore":"22151","endTimeSeconds":"1699812000"},{"territoryWarId":"tw01C","score":"20156","power":324955289,"opponentScore":"11812","endTimeSeconds":"1698598813"}],"lastRaidPointsSummary":[{"identifier":{"campaignId":"GUILD","campaignMapId":"RAIDS","campaignNodeId":"KRAYTDRAGON","campaignNodeDifficulty":4,"campaignMissionId":"DIFF01"},"totalPoints":"46634369"}],"profile":{"messageCriteriaKey":[],"raidLaunchConfig":[],"guildEventTracker":[{"definitionId":"t05D","completedStars":"21","endTime":"1699203600000"}],"id":"7skNKIClReOBSq8jfL_F0g","name":"Feddy","externalMessageKey":"Entry lvl: 4.5+mil, GL(s), 18+ https:\/\/discord.gg\/UmM2ZHTdMB","logoBackground":"","enrollmentStatus":2,"trophy":0,"memberCount":50,"memberMax":50,"level":1,"rank":0,"levelRequirement":85,"raidWin":0,"leaderboardScore":"0","bannerColorId":"green_dark_green","bannerLogoId":"guild_icon_Rebel","guildGalacticPower":"340436732","chatChannelId":"guild-{7skNKIClReOBSq8jfL_F0g}","guildType":"","guildGalacticPowerForRequirement":"340436732","singleLaunchConfig":{"raidId":"sith_raid","campaignMissionIdentifier":{"campaignId":"GUILD","campaignMapId":"RAIDS","campaignNodeId":"SITH_RAID","campaignNodeDifficulty":4,"campaignMissionId":"HEROIC85"},"autoLaunch":false,"autoLaunchImmediately":false,"autoLaunchTime":"0","joinPeriodDuration":"0","autoSimEnabled":false,"immediate":true,"scheduledUtcOffsetSeconds":"0"},"autoLaunchConfig":{"raidId":"kraytdragon","campaignMissionIdentifier":{"campaignId":"GUILD","campaignMapId":"RAIDS","campaignNodeId":"KRAYTDRAGON","campaignNodeDifficulty":4,"campaignMissionId":"DIFF01"},"autoLaunch":true,"autoLaunchImmediately":false,"autoLaunchTime":"0","joinPeriodDuration":"0","autoSimEnabled":false,"immediate":true,"scheduledUtcOffsetSeconds":"0"}},"inventory":null,"progress":null,"nextChallengesRefresh":"1699921800"}}